{
  "users": [
    {
      "id": 1,
      "name": "Selvi Vivek",
      "email": "selvi1@techmail.com",
      "username": "selvi1"
    },
    {
      "id": 2,
      "name": "Inba Sundaram",
      "email": "inba2@techmail.com",
      "username": "inba2"
    },
    {
      "id": 3,
      "name": "Jenifer Mageshwari",
      "email": "jenifer3@techmail.com",
      "username": "jenifer3"
    },
    {
      "id": 4,
      "name": "Vijay Selvi",
      "email": "vijay4@techmail.com",
      "username": "vijay4"
    },
    {
      "id": 5,
      "name": "Karthik Sundaram",
      "email": "karthik5@techmail.com",
      "username": "karthik5"
    },
    {
      "id": 6,
      "name": "Anbu Senthil",
      "email": "anbu6@techmail.com",
      "username": "anbu6"
    },
    {
      "id": 7,
      "name": "Anbu Raj",
      "email": "anbu7@techmail.com",
      "username": "anbu7"
    },
    {
      "id": 8,
      "name": "Jenifer Murugan",
      "email": "jenifer8@techmail.com",
      "username": "jenifer8"
    },
    {
      "id": 9,
      "name": "Hari Arumugam",
      "email": "hari9@techmail.com",
      "username": "hari9"
    },
    {
      "id": 10,
      "name": "Dharan Pandian",
      "email": "dharan10@techmail.com",
      "username": "dharan10"
    },
    {
      "id": 11,
      "name": "Kumar Subramanian",
      "email": "kumar11@techmail.com",
      "username": "kumar11"
    },
    {
      "id": 12,
      "name": "Valli Senthil",
      "email": "valli12@techmail.com",
      "username": "valli12"
    },
    {
      "id": 13,
      "name": "Kala Rajan",
      "email": "kala13@techmail.com",
      "username": "kala13"
    },
    {
      "id": 14,
      "name": "Senthil Senthil",
      "email": "senthil14@techmail.com",
      "username": "senthil14"
    },
    {
      "id": 15,
      "name": "Meena Raj",
      "email": "meena15@techmail.com",
      "username": "meena15"
    },
    {
      "id": 16,
      "name": "Ravi Murugan",
      "email": "ravi16@techmail.com",
      "username": "ravi16"
    },
    {
      "id": 17,
      "name": "Anbu Murugan",
      "email": "anbu17@techmail.com",
      "username": "anbu17"
    },
    {
      "id": 18,
      "name": "Vijay Sundaram",
      "email": "vijay18@techmail.com",
      "username": "vijay18"
    },
    {
      "id": 19,
      "name": "Karthik Selvi",
      "email": "karthik19@techmail.com",
      "username": "karthik19"
    },
    {
      "id": 20,
      "name": "Inba Annamalai",
      "email": "inba20@techmail.com",
      "username": "inba20"
    },
    {
      "id": 21,
      "name": "Karthik Sundaram",
      "email": "karthik21@techmail.com",
      "username": "karthik21"
    },
    {
      "id": 22,
      "name": "Sowmiya Rajan",
      "email": "sowmiya22@techmail.com",
      "username": "sowmiya22"
    },
    {
      "id": 23,
      "name": "Surya Selvi",
      "email": "surya23@techmail.com",
      "username": "surya23"
    },
    {
      "id": 24,
      "name": "Selvi Arumugam",
      "email": "selvi24@techmail.com",
      "username": "selvi24"
    },
    {
      "id": 25,
      "name": "Kannan Selvan",
      "email": "kannan25@techmail.com",
      "username": "kannan25"
    },
    {
      "id": 26,
      "name": "Thangam Rajan",
      "email": "thangam26@techmail.com",
      "username": "thangam26"
    },
    {
      "id": 27,
      "name": "Kumar Annamalai",
      "email": "kumar27@techmail.com",
      "username": "kumar27"
    },
    {
      "id": 28,
      "name": "Arjun Mageshwari",
      "email": "arjun28@techmail.com",
      "username": "arjun28"
    },
    {
      "id": 29,
      "name": "Kannan Boopalan",
      "email": "kannan29@techmail.com",
      "username": "kannan29"
    },
    {
      "id": 30,
      "name": "Meena Raj",
      "email": "meena30@techmail.com",
      "username": "meena30"
    },
    {
      "id": 31,
      "name": "Senthil Annamalai",
      "email": "senthil31@techmail.com",
      "username": "senthil31"
    },
    {
      "id": 32,
      "name": "Tamil Senthil",
      "email": "tamil32@techmail.com",
      "username": "tamil32"
    },
    {
      "id": 33,
      "name": "Anbu Rajan",
      "email": "anbu33@techmail.com",
      "username": "anbu33"
    },
    {
      "id": 34,
      "name": "Prakash Palani",
      "email": "prakash34@techmail.com",
      "username": "prakash34"
    },
    {
      "id": 35,
      "name": "Devi Selvi",
      "email": "devi35@techmail.com",
      "username": "devi35"
    },
    {
      "id": 36,
      "name": "Kumar Elango",
      "email": "kumar36@techmail.com",
      "username": "kumar36"
    },
    {
      "id": 37,
      "name": "Karthik Sundaram",
      "email": "karthik37@techmail.com",
      "username": "karthik37"
    },
    {
      "id": 38,
      "name": "Kala Venkatesh",
      "email": "kala38@techmail.com",
      "username": "kala38"
    },
    {
      "id": 39,
      "name": "Surya Krishnan",
      "email": "surya39@techmail.com",
      "username": "surya39"
    },
    {
      "id": 40,
      "name": "Priya Krishnan",
      "email": "priya40@techmail.com",
      "username": "priya40"
    },
    {
      "id": 41,
      "name": "Priya Selvan",
      "email": "priya41@techmail.com",
      "username": "priya41"
    },
    {
      "id": 42,
      "name": "Surya Rajan",
      "email": "surya42@techmail.com",
      "username": "surya42"
    },
    {
      "id": 43,
      "name": "Sowmiya Raj",
      "email": "sowmiya43@techmail.com",
      "username": "sowmiya43"
    },
    {
      "id": 44,
      "name": "Surya Selvi",
      "email": "surya44@techmail.com",
      "username": "surya44"
    },
    {
      "id": 45,
      "name": "Valli Venkatesh",
      "email": "valli45@techmail.com",
      "username": "valli45"
    },
    {
      "id": 46,
      "name": "Valli Sekhar",
      "email": "valli46@techmail.com",
      "username": "valli46"
    },
    {
      "id": 47,
      "name": "Valli Velan",
      "email": "valli47@techmail.com",
      "username": "valli47"
    },
    {
      "id": 48,
      "name": "Ganesh Elango",
      "email": "ganesh48@techmail.com",
      "username": "ganesh48"
    },
    {
      "id": 49,
      "name": "Hari Krishnan",
      "email": "hari49@techmail.com",
      "username": "hari49"
    },
    {
      "id": 50,
      "name": "Kumar Arumugam",
      "email": "kumar50@techmail.com",
      "username": "kumar50"
    }
  ],
  "posts": [
    {
      "id": 1,
      "userId": 50,
      "title": "Sustainable Tech Solutions",
      "body": "Exploring the impact of Sustainable Tech Solutions in Coimbatore...",
      "comments": [
        {
          "id": 10,
          "postId": 1,
          "userId": 1,
          "text": "Great insights about the tech scene in Tamil Nadu!"
        },
        {
          "id": 11,
          "postId": 1,
          "userId": 25,
          "text": "Great insights about the tech scene in Tamil Nadu!"
        },
        {
          "id": 12,
          "postId": 1,
          "userId": 16,
          "text": "Great insights about the tech scene in Tamil Nadu!"
        }
      ]
    },
    {
      "id": 2,
      "userId": 28,
      "title": "Traditional Tech Meets Modern",
      "body": "Exploring the impact of Traditional Tech Meets Modern in Thoothukudi...",
      "comments": [
        {
          "id": 20,
          "postId": 2,
          "userId": 36,
          "text": "Great insights about the tech scene in Tamil Nadu!"
        },
        {
          "id": 21,
          "postId": 2,
          "userId": 23,
          "text": "Great insights about the tech scene in Tamil Nadu!"
        },
        {
          "id": 22,
          "postId": 2,
          "userId": 25,
          "text": "Great insights about the tech scene in Tamil Nadu!"
        }
      ]
    },
    {
      "id": 3,
      "userId": 31,
      "title": "Healthcare Innovation",
      "body": "Exploring the impact of Healthcare Innovation in Salem...",
      "comments": [
        {
          "id": 30,
          "postId": 3,
          "userId": 3,
          "text": "Great insights about the tech scene in Tamil Nadu!"
        },
        {
          "id": 31,
          "postId": 3,
          "userId": 28,
          "text": "Great insights about the tech scene in Tamil Nadu!"
        }
      ]
    },
    {
      "id": 4,
      "userId": 1,
      "title": "Traditional Tech Meets Modern",
      "body": "Exploring the impact of Traditional Tech Meets Modern in Vellore...",
      "comments": [
        {
          "id": 40,
          "postId": 4,
          "userId": 29,
          "text": "Great insights about the tech scene in Tamil Nadu!"
        },
        {
          "id": 41,
          "postId": 4,
          "userId": 19,
          "text": "Great insights about the tech scene in Tamil Nadu!"
        },
        {
          "id": 42,
          "postId": 4,
          "userId": 34,
          "text": "Great insights about the tech scene in Tamil Nadu!"
        }
      ]
    },
    {
      "id": 5,
      "userId": 45,
      "title": "Healthcare Innovation",
      "body": "Exploring the impact of Healthcare Innovation in Tirunelveli...",
      "comments": [
        {
          "id": 50,
          "postId": 5,
          "userId": 47,
          "text": "Great insights about the tech scene in Tamil Nadu!"
        },
        {
          "id": 51,
          "postId": 5,
          "userId": 46,
          "text": "Great insights about the tech scene in Tamil Nadu!"
        }
      ]
    },
    {
      "id": 6,
      "userId": 25,
      "title": "Education Technology",
      "body": "Exploring the impact of Education Technology in Vellore...",
      "comments": [
        {
          "id": 60,
          "postId": 6,
          "userId": 35,
          "text": "Great insights about the tech scene in Tamil Nadu!"
        }
      ]
    },
    {
      "id": 7,
      "userId": 3,
      "title": "Healthcare Innovation",
      "body": "Exploring the impact of Healthcare Innovation in Salem...",
      "comments": [
        {
          "id": 70,
          "postId": 7,
          "userId": 7,
          "text": "Great insights about the tech scene in Tamil Nadu!"
        }
      ]
    },
    {
      "id": 8,
      "userId": 14,
      "title": "Sustainable Tech Solutions",
      "body": "Exploring the impact of Sustainable Tech Solutions in Madurai...",
      "comments": [
        {
          "id": 80,
          "postId": 8,
          "userId": 11,
          "text": "Great insights about the tech scene in Tamil Nadu!"
        },
        {
          "id": 81,
          "postId": 8,
          "userId": 2,
          "text": "Great insights about the tech scene in Tamil Nadu!"
        }
      ]
    },
    {
      "id": 9,
      "userId": 42,
      "title": "Sustainable Tech Solutions",
      "body": "Exploring the impact of Sustainable Tech Solutions in Thoothukudi...",
      "comments": [
        {
          "id": 90,
          "postId": 9,
          "userId": 11,
          "text": "Great insights about the tech scene in Tamil Nadu!"
        }
      ]
    },
    {
      "id": 10,
      "userId": 49,
      "title": "Traditional Tech Meets Modern",
      "body": "Exploring the impact of Traditional Tech Meets Modern in Neyveli...",
      "comments": [
        {
          "id": 100,
          "postId": 10,
          "userId": 38,
          "text": "Great insights about the tech scene in Tamil Nadu!"
        },
        {
          "id": 101,
          "postId": 10,
          "userId": 1,
          "text": "Great insights about the tech scene in Tamil Nadu!"
        },
        {
          "id": 102,
          "postId": 10,
          "userId": 40,
          "text": "Great insights about the tech scene in Tamil Nadu!"
        }
      ]
    },
    {
      "id": 11,
      "userId": 28,
      "title": "Tech Innovation in Tamil Nadu",
      "body": "Exploring the impact of Tech Innovation in Tamil Nadu in Neyveli...",
      "comments": [
        {
          "id": 110,
          "postId": 11,
          "userId": 35,
          "text": "Great insights about the tech scene in Tamil Nadu!"
        },
        {
          "id": 111,
          "postId": 11,
          "userId": 13,
          "text": "Great insights about the tech scene in Tamil Nadu!"
        }
      ]
    },
    {
      "id": 12,
      "userId": 9,
      "title": "Tech Innovation in Tamil Nadu",
      "body": "Exploring the impact of Tech Innovation in Tamil Nadu in Erode...",
      "comments": [
        {
          "id": 120,
          "postId": 12,
          "userId": 13,
          "text": "Great insights about the tech scene in Tamil Nadu!"
        },
        {
          "id": 121,
          "postId": 12,
          "userId": 1,
          "text": "Great insights about the tech scene in Tamil Nadu!"
        }
      ]
    },
    {
      "id": 13,
      "userId": 41,
      "title": "Tech Innovation in Tamil Nadu",
      "body": "Exploring the impact of Tech Innovation in Tamil Nadu in Madurai...",
      "comments": [
        {
          "id": 130,
          "postId": 13,
          "userId": 28,
          "text": "Great insights about the tech scene in Tamil Nadu!"
        }
      ]
    },
    {
      "id": 14,
      "userId": 46,
      "title": "Sustainable Tech Solutions",
      "body": "Exploring the impact of Sustainable Tech Solutions in Tirunelveli...",
      "comments": [
        {
          "id": 140,
          "postId": 14,
          "userId": 9,
          "text": "Great insights about the tech scene in Tamil Nadu!"
        }
      ]
    },
    {
      "id": 15,
      "userId": 16,
      "title": "Sustainable Tech Solutions",
      "body": "Exploring the impact of Sustainable Tech Solutions in Salem...",
      "comments": [
        {
          "id": 150,
          "postId": 15,
          "userId": 48,
          "text": "Great insights about the tech scene in Tamil Nadu!"
        }
      ]
    },
    {
      "id": 16,
      "userId": 40,
      "title": "Rural Tech Development",
      "body": "Exploring the impact of Rural Tech Development in Erode...",
      "comments": [
        {
          "id": 160,
          "postId": 16,
          "userId": 49,
          "text": "Great insights about the tech scene in Tamil Nadu!"
        },
        {
          "id": 161,
          "postId": 16,
          "userId": 31,
          "text": "Great insights about the tech scene in Tamil Nadu!"
        },
        {
          "id": 162,
          "postId": 16,
          "userId": 26,
          "text": "Great insights about the tech scene in Tamil Nadu!"
        }
      ]
    },
    {
      "id": 17,
      "userId": 20,
      "title": "Traditional Tech Meets Modern",
      "body": "Exploring the impact of Traditional Tech Meets Modern in Tirunelveli...",
      "comments": [
        {
          "id": 170,
          "postId": 17,
          "userId": 12,
          "text": "Great insights about the tech scene in Tamil Nadu!"
        },
        {
          "id": 171,
          "postId": 17,
          "userId": 35,
          "text": "Great insights about the tech scene in Tamil Nadu!"
        },
        {
          "id": 172,
          "postId": 17,
          "userId": 45,
          "text": "Great insights about the tech scene in Tamil Nadu!"
        }
      ]
    },
    {
      "id": 18,
      "userId": 9,
      "title": "Education Technology",
      "body": "Exploring the impact of Education Technology in Tiruchirappalli...",
      "comments": [
        {
          "id": 180,
          "postId": 18,
          "userId": 35,
          "text": "Great insights about the tech scene in Tamil Nadu!"
        }
      ]
    },
    {
      "id": 19,
      "userId": 8,
      "title": "Traditional Tech Meets Modern",
      "body": "Exploring the impact of Traditional Tech Meets Modern in Tirunelveli...",
      "comments": [
        {
          "id": 190,
          "postId": 19,
          "userId": 36,
          "text": "Great insights about the tech scene in Tamil Nadu!"
        },
        {
          "id": 191,
          "postId": 19,
          "userId": 41,
          "text": "Great insights about the tech scene in Tamil Nadu!"
        },
        {
          "id": 192,
          "postId": 19,
          "userId": 5,
          "text": "Great insights about the tech scene in Tamil Nadu!"
        }
      ]
    },
    {
      "id": 20,
      "userId": 45,
      "title": "Traditional Tech Meets Modern",
      "body": "Exploring the impact of Traditional Tech Meets Modern in Erode...",
      "comments": [
        {
          "id": 200,
          "postId": 20,
          "userId": 49,
          "text": "Great insights about the tech scene in Tamil Nadu!"
        }
      ]
    },
    {
      "id": 21,
      "userId": 34,
      "title": "Education Technology",
      "body": "Exploring the impact of Education Technology in Tiruchirappalli...",
      "comments": [
        {
          "id": 210,
          "postId": 21,
          "userId": 7,
          "text": "Great insights about the tech scene in Tamil Nadu!"
        },
        {
          "id": 211,
          "postId": 21,
          "userId": 12,
          "text": "Great insights about the tech scene in Tamil Nadu!"
        }
      ]
    },
    {
      "id": 22,
      "userId": 19,
      "title": "Healthcare Innovation",
      "body": "Exploring the impact of Healthcare Innovation in Neyveli...",
      "comments": [
        {
          "id": 220,
          "postId": 22,
          "userId": 45,
          "text": "Great insights about the tech scene in Tamil Nadu!"
        },
        {
          "id": 221,
          "postId": 22,
          "userId": 33,
          "text": "Great insights about the tech scene in Tamil Nadu!"
        },
        {
          "id": 222,
          "postId": 22,
          "userId": 17,
          "text": "Great insights about the tech scene in Tamil Nadu!"
        }
      ]
    },
    {
      "id": 23,
      "userId": 45,
      "title": "Education Technology",
      "body": "Exploring the impact of Education Technology in Neyveli...",
      "comments": [
        {
          "id": 230,
          "postId": 23,
          "userId": 1,
          "text": "Great insights about the tech scene in Tamil Nadu!"
        },
        {
          "id": 231,
          "postId": 23,
          "userId": 15,
          "text": "Great insights about the tech scene in Tamil Nadu!"
        },
        {
          "id": 232,
          "postId": 23,
          "userId": 47,
          "text": "Great insights about the tech scene in Tamil Nadu!"
        }
      ]
    },
    {
      "id": 24,
      "userId": 11,
      "title": "Traditional Tech Meets Modern",
      "body": "Exploring the impact of Traditional Tech Meets Modern in Coimbatore...",
      "comments": [
        {
          "id": 240,
          "postId": 24,
          "userId": 49,
          "text": "Great insights about the tech scene in Tamil Nadu!"
        },
        {
          "id": 241,
          "postId": 24,
          "userId": 41,
          "text": "Great insights about the tech scene in Tamil Nadu!"
        }
      ]
    },
    {
      "id": 25,
      "userId": 12,
      "title": "Sustainable Tech Solutions",
      "body": "Exploring the impact of Sustainable Tech Solutions in Tiruchirappalli...",
      "comments": [
        {
          "id": 250,
          "postId": 25,
          "userId": 34,
          "text": "Great insights about the tech scene in Tamil Nadu!"
        },
        {
          "id": 251,
          "postId": 25,
          "userId": 23,
          "text": "Great insights about the tech scene in Tamil Nadu!"
        },
        {
          "id": 252,
          "postId": 25,
          "userId": 8,
          "text": "Great insights about the tech scene in Tamil Nadu!"
        }
      ]
    },
    {
      "id": 26,
      "userId": 10,
      "title": "Education Technology",
      "body": "Exploring the impact of Education Technology in Madurai...",
      "comments": [
        {
          "id": 260,
          "postId": 26,
          "userId": 20,
          "text": "Great insights about the tech scene in Tamil Nadu!"
        },
        {
          "id": 261,
          "postId": 26,
          "userId": 16,
          "text": "Great insights about the tech scene in Tamil Nadu!"
        },
        {
          "id": 262,
          "postId": 26,
          "userId": 47,
          "text": "Great insights about the tech scene in Tamil Nadu!"
        }
      ]
    },
    {
      "id": 27,
      "userId": 5,
      "title": "Digital Transformation",
      "body": "Exploring the impact of Digital Transformation in Salem...",
      "comments": [
        {
          "id": 270,
          "postId": 27,
          "userId": 25,
          "text": "Great insights about the tech scene in Tamil Nadu!"
        }
      ]
    },
    {
      "id": 28,
      "userId": 30,
      "title": "Digital Transformation",
      "body": "Exploring the impact of Digital Transformation in Thanjavur...",
      "comments": [
        {
          "id": 280,
          "postId": 28,
          "userId": 28,
          "text": "Great insights about the tech scene in Tamil Nadu!"
        },
        {
          "id": 281,
          "postId": 28,
          "userId": 19,
          "text": "Great insights about the tech scene in Tamil Nadu!"
        }
      ]
    },
    {
      "id": 29,
      "userId": 43,
      "title": "Traditional Tech Meets Modern",
      "body": "Exploring the impact of Traditional Tech Meets Modern in Tirunelveli...",
      "comments": [
        {
          "id": 290,
          "postId": 29,
          "userId": 5,
          "text": "Great insights about the tech scene in Tamil Nadu!"
        }
      ]
    },
    {
      "id": 30,
      "userId": 39,
      "title": "Smart City Initiatives",
      "body": "Exploring the impact of Smart City Initiatives in Tirunelveli...",
      "comments": [
        {
          "id": 300,
          "postId": 30,
          "userId": 37,
          "text": "Great insights about the tech scene in Tamil Nadu!"
        },
        {
          "id": 301,
          "postId": 30,
          "userId": 3,
          "text": "Great insights about the tech scene in Tamil Nadu!"
        }
      ]
    },
    {
      "id": 31,
      "userId": 28,
      "title": "Startup Scene in Chennai",
      "body": "Exploring the impact of Startup Scene in Chennai in Madurai...",
      "comments": [
        {
          "id": 310,
          "postId": 31,
          "userId": 50,
          "text": "Great insights about the tech scene in Tamil Nadu!"
        },
        {
          "id": 311,
          "postId": 31,
          "userId": 17,
          "text": "Great insights about the tech scene in Tamil Nadu!"
        },
        {
          "id": 312,
          "postId": 31,
          "userId": 9,
          "text": "Great insights about the tech scene in Tamil Nadu!"
        }
      ]
    },
    {
      "id": 32,
      "userId": 8,
      "title": "Traditional Tech Meets Modern",
      "body": "Exploring the impact of Traditional Tech Meets Modern in Thoothukudi...",
      "comments": [
        {
          "id": 320,
          "postId": 32,
          "userId": 21,
          "text": "Great insights about the tech scene in Tamil Nadu!"
        }
      ]
    },
    {
      "id": 33,
      "userId": 4,
      "title": "Traditional Tech Meets Modern",
      "body": "Exploring the impact of Traditional Tech Meets Modern in Tirunelveli...",
      "comments": [
        {
          "id": 330,
          "postId": 33,
          "userId": 20,
          "text": "Great insights about the tech scene in Tamil Nadu!"
        },
        {
          "id": 331,
          "postId": 33,
          "userId": 27,
          "text": "Great insights about the tech scene in Tamil Nadu!"
        },
        {
          "id": 332,
          "postId": 33,
          "userId": 34,
          "text": "Great insights about the tech scene in Tamil Nadu!"
        }
      ]
    },
    {
      "id": 34,
      "userId": 3,
      "title": "Startup Scene in Chennai",
      "body": "Exploring the impact of Startup Scene in Chennai in Erode...",
      "comments": [
        {
          "id": 340,
          "postId": 34,
          "userId": 22,
          "text": "Great insights about the tech scene in Tamil Nadu!"
        }
      ]
    },
    {
      "id": 35,
      "userId": 20,
      "title": "Startup Scene in Chennai",
      "body": "Exploring the impact of Startup Scene in Chennai in Erode...",
      "comments": [
        {
          "id": 350,
          "postId": 35,
          "userId": 2,
          "text": "Great insights about the tech scene in Tamil Nadu!"
        },
        {
          "id": 351,
          "postId": 35,
          "userId": 23,
          "text": "Great insights about the tech scene in Tamil Nadu!"
        },
        {
          "id": 352,
          "postId": 35,
          "userId": 28,
          "text": "Great insights about the tech scene in Tamil Nadu!"
        }
      ]
    },
    {
      "id": 36,
      "userId": 8,
      "title": "Sustainable Tech Solutions",
      "body": "Exploring the impact of Sustainable Tech Solutions in Madurai...",
      "comments": [
        {
          "id": 360,
          "postId": 36,
          "userId": 14,
          "text": "Great insights about the tech scene in Tamil Nadu!"
        },
        {
          "id": 361,
          "postId": 36,
          "userId": 18,
          "text": "Great insights about the tech scene in Tamil Nadu!"
        },
        {
          "id": 362,
          "postId": 36,
          "userId": 44,
          "text": "Great insights about the tech scene in Tamil Nadu!"
        }
      ]
    },
    {
      "id": 37,
      "userId": 23,
      "title": "Startup Scene in Chennai",
      "body": "Exploring the impact of Startup Scene in Chennai in Thoothukudi...",
      "comments": [
        {
          "id": 370,
          "postId": 37,
          "userId": 25,
          "text": "Great insights about the tech scene in Tamil Nadu!"
        },
        {
          "id": 371,
          "postId": 37,
          "userId": 32,
          "text": "Great insights about the tech scene in Tamil Nadu!"
        }
      ]
    },
    {
      "id": 38,
      "userId": 45,
      "title": "Education Technology",
      "body": "Exploring the impact of Education Technology in Tiruchirappalli...",
      "comments": [
        {
          "id": 380,
          "postId": 38,
          "userId": 13,
          "text": "Great insights about the tech scene in Tamil Nadu!"
        }
      ]
    },
    {
      "id": 39,
      "userId": 23,
      "title": "Education Technology",
      "body": "Exploring the impact of Education Technology in Chennai...",
      "comments": [
        {
          "id": 390,
          "postId": 39,
          "userId": 48,
          "text": "Great insights about the tech scene in Tamil Nadu!"
        },
        {
          "id": 391,
          "postId": 39,
          "userId": 30,
          "text": "Great insights about the tech scene in Tamil Nadu!"
        },
        {
          "id": 392,
          "postId": 39,
          "userId": 50,
          "text": "Great insights about the tech scene in Tamil Nadu!"
        }
      ]
    },
    {
      "id": 40,
      "userId": 37,
      "title": "Startup Scene in Chennai",
      "body": "Exploring the impact of Startup Scene in Chennai in Madurai...",
      "comments": [
        {
          "id": 400,
          "postId": 40,
          "userId": 3,
          "text": "Great insights about the tech scene in Tamil Nadu!"
        },
        {
          "id": 401,
          "postId": 40,
          "userId": 42,
          "text": "Great insights about the tech scene in Tamil Nadu!"
        },
        {
          "id": 402,
          "postId": 40,
          "userId": 31,
          "text": "Great insights about the tech scene in Tamil Nadu!"
        }
      ]
    },
    {
      "id": 41,
      "userId": 20,
      "title": "Traditional Tech Meets Modern",
      "body": "Exploring the impact of Traditional Tech Meets Modern in Thanjavur...",
      "comments": [
        {
          "id": 410,
          "postId": 41,
          "userId": 7,
          "text": "Great insights about the tech scene in Tamil Nadu!"
        },
        {
          "id": 411,
          "postId": 41,
          "userId": 37,
          "text": "Great insights about the tech scene in Tamil Nadu!"
        }
      ]
    },
    {
      "id": 42,
      "userId": 39,
      "title": "Rural Tech Development",
      "body": "Exploring the impact of Rural Tech Development in Coimbatore...",
      "comments": [
        {
          "id": 420,
          "postId": 42,
          "userId": 14,
          "text": "Great insights about the tech scene in Tamil Nadu!"
        },
        {
          "id": 421,
          "postId": 42,
          "userId": 32,
          "text": "Great insights about the tech scene in Tamil Nadu!"
        },
        {
          "id": 422,
          "postId": 42,
          "userId": 24,
          "text": "Great insights about the tech scene in Tamil Nadu!"
        }
      ]
    },
    {
      "id": 43,
      "userId": 13,
      "title": "Digital Transformation",
      "body": "Exploring the impact of Digital Transformation in Thanjavur...",
      "comments": [
        {
          "id": 430,
          "postId": 43,
          "userId": 32,
          "text": "Great insights about the tech scene in Tamil Nadu!"
        },
        {
          "id": 431,
          "postId": 43,
          "userId": 28,
          "text": "Great insights about the tech scene in Tamil Nadu!"
        }
      ]
    },
    {
      "id": 44,
      "userId": 38,
      "title": "Tech Innovation in Tamil Nadu",
      "body": "Exploring the impact of Tech Innovation in Tamil Nadu in Thanjavur...",
      "comments": [
        {
          "id": 440,
          "postId": 44,
          "userId": 26,
          "text": "Great insights about the tech scene in Tamil Nadu!"
        }
      ]
    },
    {
      "id": 45,
      "userId": 18,
      "title": "Digital Transformation",
      "body": "Exploring the impact of Digital Transformation in Tiruchirappalli...",
      "comments": [
        {
          "id": 450,
          "postId": 45,
          "userId": 32,
          "text": "Great insights about the tech scene in Tamil Nadu!"
        },
        {
          "id": 451,
          "postId": 45,
          "userId": 37,
          "text": "Great insights about the tech scene in Tamil Nadu!"
        }
      ]
    },
    {
      "id": 46,
      "userId": 23,
      "title": "Healthcare Innovation",
      "body": "Exploring the impact of Healthcare Innovation in Madurai...",
      "comments": [
        {
          "id": 460,
          "postId": 46,
          "userId": 38,
          "text": "Great insights about the tech scene in Tamil Nadu!"
        }
      ]
    },
    {
      "id": 47,
      "userId": 31,
      "title": "Tech Innovation in Tamil Nadu",
      "body": "Exploring the impact of Tech Innovation in Tamil Nadu in Thoothukudi...",
      "comments": [
        {
          "id": 470,
          "postId": 47,
          "userId": 49,
          "text": "Great insights about the tech scene in Tamil Nadu!"
        }
      ]
    },
    {
      "id": 48,
      "userId": 4,
      "title": "Startup Scene in Chennai",
      "body": "Exploring the impact of Startup Scene in Chennai in Neyveli...",
      "comments": [
        {
          "id": 480,
          "postId": 48,
          "userId": 38,
          "text": "Great insights about the tech scene in Tamil Nadu!"
        }
      ]
    },
    {
      "id": 49,
      "userId": 3,
      "title": "Tech Innovation in Tamil Nadu",
      "body": "Exploring the impact of Tech Innovation in Tamil Nadu in Thanjavur...",
      "comments": [
        {
          "id": 490,
          "postId": 49,
          "userId": 21,
          "text": "Great insights about the tech scene in Tamil Nadu!"
        },
        {
          "id": 491,
          "postId": 49,
          "userId": 41,
          "text": "Great insights about the tech scene in Tamil Nadu!"
        }
      ]
    },
    {
      "id": 50,
      "userId": 8,
      "title": "Education Technology",
      "body": "Exploring the impact of Education Technology in Tirunelveli...",
      "comments": [
        {
          "id": 500,
          "postId": 50,
          "userId": 22,
          "text": "Great insights about the tech scene in Tamil Nadu!"
        },
        {
          "id": 501,
          "postId": 50,
          "userId": 39,
          "text": "Great insights about the tech scene in Tamil Nadu!"
        },
        {
          "id": 502,
          "postId": 50,
          "userId": 8,
          "text": "Great insights about the tech scene in Tamil Nadu!"
        }
      ]
    }
  ],
  "todos": [
    {
      "id": 1,
      "userId": 1,
      "task": "Update Chennai traffic monitoring system",
      "completed": false
    },
    {
      "id": 2,
      "userId": 1,
      "task": "Create e-governance portal",
      "completed": false
    },
    {
      "id": 3,
      "userId": 1,
      "task": "Create e-governance portal",
      "completed": true
    },
    {
      "id": 4,
      "userId": 2,
      "task": "Design rural healthcare platform",
      "completed": true
    },
    {
      "id": 5,
      "userId": 3,
      "task": "Update Chennai traffic monitoring system",
      "completed": false
    },
    {
      "id": 6,
      "userId": 3,
      "task": "Design rural healthcare platform",
      "completed": true
    },
    {
      "id": 7,
      "userId": 3,
      "task": "Design rural healthcare platform",
      "completed": false
    },
    {
      "id": 8,
      "userId": 4,
      "task": "Develop smart agriculture app",
      "completed": true
    },
    {
      "id": 9,
      "userId": 5,
      "task": "Implement blockchain for land records",
      "completed": false
    },
    {
      "id": 10,
      "userId": 6,
      "task": "Create e-governance portal",
      "completed": true
    },
    {
      "id": 11,
      "userId": 7,
      "task": "Implement blockchain for land records",
      "completed": true
    },
    {
      "id": 12,
      "userId": 7,
      "task": "Develop smart agriculture app",
      "completed": true
    },
    {
      "id": 13,
      "userId": 7,
      "task": "Implement blockchain for land records",
      "completed": false
    },
    {
      "id": 14,
      "userId": 8,
      "task": "Design rural healthcare platform",
      "completed": true
    },
    {
      "id": 15,
      "userId": 8,
      "task": "Implement blockchain for land records",
      "completed": true
    },
    {
      "id": 16,
      "userId": 9,
      "task": "Develop smart agriculture app",
      "completed": true
    },
    {
      "id": 17,
      "userId": 9,
      "task": "Create e-governance portal",
      "completed": true
    },
    {
      "id": 18,
      "userId": 10,
      "task": "Design rural healthcare platform",
      "completed": false
    },
    {
      "id": 19,
      "userId": 10,
      "task": "Design rural healthcare platform",
      "completed": true
    },
    {
      "id": 20,
      "userId": 11,
      "task": "Design rural healthcare platform",
      "completed": false
    },
    {
      "id": 21,
      "userId": 11,
      "task": "Create e-governance portal",
      "completed": true
    },
    {
      "id": 22,
      "userId": 11,
      "task": "Create e-governance portal",
      "completed": true
    },
    {
      "id": 23,
      "userId": 12,
      "task": "Create e-governance portal",
      "completed": true
    },
    {
      "id": 24,
      "userId": 13,
      "task": "Implement blockchain for land records",
      "completed": false
    },
    {
      "id": 25,
      "userId": 14,
      "task": "Review Tamil NLP model",
      "completed": true
    },
    {
      "id": 26,
      "userId": 14,
      "task": "Review Tamil NLP model",
      "completed": false
    },
    {
      "id": 27,
      "userId": 14,
      "task": "Develop smart agriculture app",
      "completed": false
    },
    {
      "id": 28,
      "userId": 15,
      "task": "Implement blockchain for land records",
      "completed": true
    },
    {
      "id": 29,
      "userId": 15,
      "task": "Review Tamil NLP model",
      "completed": true
    },
    {
      "id": 30,
      "userId": 16,
      "task": "Design rural healthcare platform",
      "completed": false
    },
    {
      "id": 31,
      "userId": 16,
      "task": "Update Chennai traffic monitoring system",
      "completed": true
    },
    {
      "id": 32,
      "userId": 17,
      "task": "Create e-governance portal",
      "completed": true
    },
    {
      "id": 33,
      "userId": 17,
      "task": "Implement blockchain for land records",
      "completed": false
    },
    {
      "id": 34,
      "userId": 17,
      "task": "Design rural healthcare platform",
      "completed": true
    },
    {
      "id": 35,
      "userId": 18,
      "task": "Update Chennai traffic monitoring system",
      "completed": false
    },
    {
      "id": 36,
      "userId": 19,
      "task": "Develop smart agriculture app",
      "completed": true
    },
    {
      "id": 37,
      "userId": 19,
      "task": "Review Tamil NLP model",
      "completed": false
    },
    {
      "id": 38,
      "userId": 20,
      "task": "Create e-governance portal",
      "completed": false
    },
    {
      "id": 39,
      "userId": 20,
      "task": "Design rural healthcare platform",
      "completed": true
    },
    {
      "id": 40,
      "userId": 20,
      "task": "Develop smart agriculture app",
      "completed": true
    },
    {
      "id": 41,
      "userId": 21,
      "task": "Design rural healthcare platform",
      "completed": false
    },
    {
      "id": 42,
      "userId": 22,
      "task": "Review Tamil NLP model",
      "completed": false
    },
    {
      "id": 43,
      "userId": 22,
      "task": "Update Chennai traffic monitoring system",
      "completed": true
    },
    {
      "id": 44,
      "userId": 23,
      "task": "Design rural healthcare platform",
      "completed": false
    },
    {
      "id": 45,
      "userId": 24,
      "task": "Design rural healthcare platform",
      "completed": true
    },
    {
      "id": 46,
      "userId": 24,
      "task": "Review Tamil NLP model",
      "completed": false
    },
    {
      "id": 47,
      "userId": 24,
      "task": "Implement blockchain for land records",
      "completed": false
    },
    {
      "id": 48,
      "userId": 25,
      "task": "Review Tamil NLP model",
      "completed": false
    },
    {
      "id": 49,
      "userId": 26,
      "task": "Review Tamil NLP model",
      "completed": true
    },
    {
      "id": 50,
      "userId": 27,
      "task": "Design rural healthcare platform",
      "completed": true
    },
    {
      "id": 51,
      "userId": 27,
      "task": "Implement blockchain for land records",
      "completed": false
    },
    {
      "id": 52,
      "userId": 27,
      "task": "Update Chennai traffic monitoring system",
      "completed": true
    },
    {
      "id": 53,
      "userId": 28,
      "task": "Update Chennai traffic monitoring system",
      "completed": false
    },
    {
      "id": 54,
      "userId": 29,
      "task": "Update Chennai traffic monitoring system",
      "completed": false
    },
    {
      "id": 55,
      "userId": 29,
      "task": "Update Chennai traffic monitoring system",
      "completed": false
    },
    {
      "id": 56,
      "userId": 29,
      "task": "Design rural healthcare platform",
      "completed": false
    },
    {
      "id": 57,
      "userId": 30,
      "task": "Review Tamil NLP model",
      "completed": false
    },
    {
      "id": 58,
      "userId": 30,
      "task": "Review Tamil NLP model",
      "completed": false
    },
    {
      "id": 59,
      "userId": 31,
      "task": "Implement blockchain for land records",
      "completed": false
    },
    {
      "id": 60,
      "userId": 32,
      "task": "Develop smart agriculture app",
      "completed": false
    },
    {
      "id": 61,
      "userId": 32,
      "task": "Design rural healthcare platform",
      "completed": false
    },
    {
      "id": 62,
      "userId": 33,
      "task": "Review Tamil NLP model",
      "completed": true
    },
    {
      "id": 63,
      "userId": 33,
      "task": "Create e-governance portal",
      "completed": false
    },
    {
      "id": 64,
      "userId": 33,
      "task": "Create e-governance portal",
      "completed": true
    },
    {
      "id": 65,
      "userId": 34,
      "task": "Develop smart agriculture app",
      "completed": false
    },
    {
      "id": 66,
      "userId": 34,
      "task": "Review Tamil NLP model",
      "completed": false
    },
    {
      "id": 67,
      "userId": 35,
      "task": "Design rural healthcare platform",
      "completed": false
    },
    {
      "id": 68,
      "userId": 35,
      "task": "Review Tamil NLP model",
      "completed": true
    },
    {
      "id": 69,
      "userId": 35,
      "task": "Review Tamil NLP model",
      "completed": true
    },
    {
      "id": 70,
      "userId": 36,
      "task": "Develop smart agriculture app",
      "completed": false
    },
    {
      "id": 71,
      "userId": 36,
      "task": "Review Tamil NLP model",
      "completed": false
    },
    {
      "id": 72,
      "userId": 36,
      "task": "Design rural healthcare platform",
      "completed": true
    },
    {
      "id": 73,
      "userId": 37,
      "task": "Create e-governance portal",
      "completed": false
    },
    {
      "id": 74,
      "userId": 37,
      "task": "Create e-governance portal",
      "completed": true
    },
    {
      "id": 75,
      "userId": 38,
      "task": "Review Tamil NLP model",
      "completed": false
    },
    {
      "id": 76,
      "userId": 38,
      "task": "Create e-governance portal",
      "completed": true
    },
    {
      "id": 77,
      "userId": 39,
      "task": "Design rural healthcare platform",
      "completed": false
    },
    {
      "id": 78,
      "userId": 39,
      "task": "Develop smart agriculture app",
      "completed": false
    },
    {
      "id": 79,
      "userId": 39,
      "task": "Develop smart agriculture app",
      "completed": false
    },
    {
      "id": 80,
      "userId": 40,
      "task": "Design rural healthcare platform",
      "completed": true
    },
    {
      "id": 81,
      "userId": 40,
      "task": "Design rural healthcare platform",
      "completed": false
    },
    {
      "id": 82,
      "userId": 40,
      "task": "Create e-governance portal",
      "completed": false
    },
    {
      "id": 83,
      "userId": 41,
      "task": "Update Chennai traffic monitoring system",
      "completed": true
    },
    {
      "id": 84,
      "userId": 41,
      "task": "Create e-governance portal",
      "completed": false
    },
    {
      "id": 85,
      "userId": 41,
      "task": "Develop smart agriculture app",
      "completed": false
    },
    {
      "id": 86,
      "userId": 42,
      "task": "Design rural healthcare platform",
      "completed": true
    },
    {
      "id": 87,
      "userId": 42,
      "task": "Implement blockchain for land records",
      "completed": false
    },
    {
      "id": 88,
      "userId": 43,
      "task": "Develop smart agriculture app",
      "completed": false
    },
    {
      "id": 89,
      "userId": 44,
      "task": "Develop smart agriculture app",
      "completed": true
    },
    {
      "id": 90,
      "userId": 45,
      "task": "Develop smart agriculture app",
      "completed": true
    },
    {
      "id": 91,
      "userId": 45,
      "task": "Create e-governance portal",
      "completed": false
    },
    {
      "id": 92,
      "userId": 45,
      "task": "Review Tamil NLP model",
      "completed": true
    },
    {
      "id": 93,
      "userId": 46,
      "task": "Design rural healthcare platform",
      "completed": false
    },
    {
      "id": 94,
      "userId": 46,
      "task": "Implement blockchain for land records",
      "completed": true
    },
    {
      "id": 95,
      "userId": 47,
      "task": "Implement blockchain for land records",
      "completed": false
    },
    {
      "id": 96,
      "userId": 48,
      "task": "Implement blockchain for land records",
      "completed": false
    },
    {
      "id": 97,
      "userId": 49,
      "task": "Develop smart agriculture app",
      "completed": true
    },
    {
      "id": 98,
      "userId": 49,
      "task": "Develop smart agriculture app",
      "completed": true
    },
    {
      "id": 99,
      "userId": 50,
      "task": "Design rural healthcare platform",
      "completed": true
    },
    {
      "id": 100,
      "userId": 50,
      "task": "Implement blockchain for land records",
      "completed": true
    }
  ],
  "projects": [
    {
      "id": 1,
      "name": "Thanjavur IoT Initiative",
      "userId": 7,
      "description": "Implementing IoT solutions for Thanjavur region",
      "tasks": [
        {
          "id": 10,
          "projectId": 1,
          "task": "Phase 1 Implementation",
          "status": "Completed"
        },
        {
          "id": 11,
          "projectId": 1,
          "task": "Phase 2 Implementation",
          "status": "Not Started"
        },
        {
          "id": 12,
          "projectId": 1,
          "task": "Phase 3 Implementation",
          "status": "Not Started"
        },
        {
          "id": 13,
          "projectId": 1,
          "task": "Phase 4 Implementation",
          "status": "Completed"
        }
      ]
    },
    {
      "id": 2,
      "name": "Vellore Cloud Computing Initiative",
      "userId": 36,
      "description": "Implementing Cloud Computing solutions for Vellore region",
      "tasks": [
        {
          "id": 20,
          "projectId": 2,
          "task": "Phase 1 Implementation",
          "status": "In Progress"
        },
        {
          "id": 21,
          "projectId": 2,
          "task": "Phase 2 Implementation",
          "status": "Completed"
        },
        {
          "id": 22,
          "projectId": 2,
          "task": "Phase 3 Implementation",
          "status": "Completed"
        }
      ]
    },
    {
      "id": 3,
      "name": "Tiruchirappalli Cybersecurity Initiative",
      "userId": 16,
      "description": "Implementing Cybersecurity solutions for Tiruchirappalli region",
      "tasks": [
        {
          "id": 30,
          "projectId": 3,
          "task": "Phase 1 Implementation",
          "status": "Completed"
        },
        {
          "id": 31,
          "projectId": 3,
          "task": "Phase 2 Implementation",
          "status": "Completed"
        }
      ]
    },
    {
      "id": 4,
      "name": "Neyveli Mobile App Initiative",
      "userId": 5,
      "description": "Implementing Mobile App solutions for Neyveli region",
      "tasks": [
        {
          "id": 40,
          "projectId": 4,
          "task": "Phase 1 Implementation",
          "status": "In Progress"
        },
        {
          "id": 41,
          "projectId": 4,
          "task": "Phase 2 Implementation",
          "status": "In Progress"
        },
        {
          "id": 42,
          "projectId": 4,
          "task": "Phase 3 Implementation",
          "status": "In Progress"
        },
        {
          "id": 43,
          "projectId": 4,
          "task": "Phase 4 Implementation",
          "status": "Not Started"
        }
      ]
    },
    {
      "id": 5,
      "name": "Tirunelveli Mobile App Initiative",
      "userId": 44,
      "description": "Implementing Mobile App solutions for Tirunelveli region",
      "tasks": [
        {
          "id": 50,
          "projectId": 5,
          "task": "Phase 1 Implementation",
          "status": "Completed"
        },
        {
          "id": 51,
          "projectId": 5,
          "task": "Phase 2 Implementation",
          "status": "Completed"
        },
        {
          "id": 52,
          "projectId": 5,
          "task": "Phase 3 Implementation",
          "status": "Completed"
        }
      ]
    },
    {
      "id": 6,
      "name": "Tiruchirappalli Digital Marketing Initiative",
      "userId": 13,
      "description": "Implementing Digital Marketing solutions for Tiruchirappalli region",
      "tasks": [
        {
          "id": 60,
          "projectId": 6,
          "task": "Phase 1 Implementation",
          "status": "Not Started"
        },
        {
          "id": 61,
          "projectId": 6,
          "task": "Phase 2 Implementation",
          "status": "In Progress"
        },
        {
          "id": 62,
          "projectId": 6,
          "task": "Phase 3 Implementation",
          "status": "Completed"
        },
        {
          "id": 63,
          "projectId": 6,
          "task": "Phase 4 Implementation",
          "status": "Not Started"
        }
      ]
    },
    {
      "id": 7,
      "name": "Thoothukudi Digital Marketing Initiative",
      "userId": 15,
      "description": "Implementing Digital Marketing solutions for Thoothukudi region",
      "tasks": [
        {
          "id": 70,
          "projectId": 7,
          "task": "Phase 1 Implementation",
          "status": "In Progress"
        },
        {
          "id": 71,
          "projectId": 7,
          "task": "Phase 2 Implementation",
          "status": "Not Started"
        },
        {
          "id": 72,
          "projectId": 7,
          "task": "Phase 3 Implementation",
          "status": "Completed"
        },
        {
          "id": 73,
          "projectId": 7,
          "task": "Phase 4 Implementation",
          "status": "Completed"
        }
      ]
    },
    {
      "id": 8,
      "name": "Tiruchirappalli IoT Initiative",
      "userId": 32,
      "description": "Implementing IoT solutions for Tiruchirappalli region",
      "tasks": [
        {
          "id": 80,
          "projectId": 8,
          "task": "Phase 1 Implementation",
          "status": "Not Started"
        },
        {
          "id": 81,
          "projectId": 8,
          "task": "Phase 2 Implementation",
          "status": "Not Started"
        },
        {
          "id": 82,
          "projectId": 8,
          "task": "Phase 3 Implementation",
          "status": "Not Started"
        }
      ]
    },
    {
      "id": 9,
      "name": "Tirunelveli IoT Initiative",
      "userId": 26,
      "description": "Implementing IoT solutions for Tirunelveli region",
      "tasks": [
        {
          "id": 90,
          "projectId": 9,
          "task": "Phase 1 Implementation",
          "status": "Not Started"
        },
        {
          "id": 91,
          "projectId": 9,
          "task": "Phase 2 Implementation",
          "status": "Completed"
        },
        {
          "id": 92,
          "projectId": 9,
          "task": "Phase 3 Implementation",
          "status": "Not Started"
        }
      ]
    },
    {
      "id": 10,
      "name": "Erode Mobile App Initiative",
      "userId": 25,
      "description": "Implementing Mobile App solutions for Erode region",
      "tasks": [
        {
          "id": 100,
          "projectId": 10,
          "task": "Phase 1 Implementation",
          "status": "In Progress"
        },
        {
          "id": 101,
          "projectId": 10,
          "task": "Phase 2 Implementation",
          "status": "In Progress"
        },
        {
          "id": 102,
          "projectId": 10,
          "task": "Phase 3 Implementation",
          "status": "Not Started"
        }
      ]
    },
    {
      "id": 11,
      "name": "Chennai Data Analytics Initiative",
      "userId": 46,
      "description": "Implementing Data Analytics solutions for Chennai region",
      "tasks": [
        {
          "id": 110,
          "projectId": 11,
          "task": "Phase 1 Implementation",
          "status": "Not Started"
        },
        {
          "id": 111,
          "projectId": 11,
          "task": "Phase 2 Implementation",
          "status": "Not Started"
        },
        {
          "id": 112,
          "projectId": 11,
          "task": "Phase 3 Implementation",
          "status": "In Progress"
        },
        {
          "id": 113,
          "projectId": 11,
          "task": "Phase 4 Implementation",
          "status": "Not Started"
        }
      ]
    },
    {
      "id": 12,
      "name": "Chennai IoT Initiative",
      "userId": 30,
      "description": "Implementing IoT solutions for Chennai region",
      "tasks": [
        {
          "id": 120,
          "projectId": 12,
          "task": "Phase 1 Implementation",
          "status": "Not Started"
        },
        {
          "id": 121,
          "projectId": 12,
          "task": "Phase 2 Implementation",
          "status": "Completed"
        },
        {
          "id": 122,
          "projectId": 12,
          "task": "Phase 3 Implementation",
          "status": "In Progress"
        },
        {
          "id": 123,
          "projectId": 12,
          "task": "Phase 4 Implementation",
          "status": "In Progress"
        }
      ]
    },
    {
      "id": 13,
      "name": "Thoothukudi AI/ML Initiative",
      "userId": 31,
      "description": "Implementing AI/ML solutions for Thoothukudi region",
      "tasks": [
        {
          "id": 130,
          "projectId": 13,
          "task": "Phase 1 Implementation",
          "status": "In Progress"
        },
        {
          "id": 131,
          "projectId": 13,
          "task": "Phase 2 Implementation",
          "status": "In Progress"
        },
        {
          "id": 132,
          "projectId": 13,
          "task": "Phase 3 Implementation",
          "status": "In Progress"
        },
        {
          "id": 133,
          "projectId": 13,
          "task": "Phase 4 Implementation",
          "status": "Completed"
        }
      ]
    },
    {
      "id": 14,
      "name": "Madurai Mobile App Initiative",
      "userId": 40,
      "description": "Implementing Mobile App solutions for Madurai region",
      "tasks": [
        {
          "id": 140,
          "projectId": 14,
          "task": "Phase 1 Implementation",
          "status": "Not Started"
        },
        {
          "id": 141,
          "projectId": 14,
          "task": "Phase 2 Implementation",
          "status": "Not Started"
        },
        {
          "id": 142,
          "projectId": 14,
          "task": "Phase 3 Implementation",
          "status": "Completed"
        },
        {
          "id": 143,
          "projectId": 14,
          "task": "Phase 4 Implementation",
          "status": "In Progress"
        }
      ]
    },
    {
      "id": 15,
      "name": "Coimbatore E-commerce Initiative",
      "userId": 23,
      "description": "Implementing E-commerce solutions for Coimbatore region",
      "tasks": [
        {
          "id": 150,
          "projectId": 15,
          "task": "Phase 1 Implementation",
          "status": "In Progress"
        },
        {
          "id": 151,
          "projectId": 15,
          "task": "Phase 2 Implementation",
          "status": "In Progress"
        }
      ]
    },
    {
      "id": 16,
      "name": "Tirunelveli Blockchain Initiative",
      "userId": 5,
      "description": "Implementing Blockchain solutions for Tirunelveli region",
      "tasks": [
        {
          "id": 160,
          "projectId": 16,
          "task": "Phase 1 Implementation",
          "status": "Not Started"
        },
        {
          "id": 161,
          "projectId": 16,
          "task": "Phase 2 Implementation",
          "status": "Completed"
        },
        {
          "id": 162,
          "projectId": 16,
          "task": "Phase 3 Implementation",
          "status": "Not Started"
        }
      ]
    },
    {
      "id": 17,
      "name": "Tiruchirappalli Cloud Computing Initiative",
      "userId": 30,
      "description": "Implementing Cloud Computing solutions for Tiruchirappalli region",
      "tasks": [
        {
          "id": 170,
          "projectId": 17,
          "task": "Phase 1 Implementation",
          "status": "Completed"
        },
        {
          "id": 171,
          "projectId": 17,
          "task": "Phase 2 Implementation",
          "status": "In Progress"
        },
        {
          "id": 172,
          "projectId": 17,
          "task": "Phase 3 Implementation",
          "status": "Completed"
        },
        {
          "id": 173,
          "projectId": 17,
          "task": "Phase 4 Implementation",
          "status": "Completed"
        }
      ]
    },
    {
      "id": 18,
      "name": "Chennai Digital Marketing Initiative",
      "userId": 42,
      "description": "Implementing Digital Marketing solutions for Chennai region",
      "tasks": [
        {
          "id": 180,
          "projectId": 18,
          "task": "Phase 1 Implementation",
          "status": "Completed"
        },
        {
          "id": 181,
          "projectId": 18,
          "task": "Phase 2 Implementation",
          "status": "Not Started"
        }
      ]
    },
    {
      "id": 19,
      "name": "Tiruchirappalli AI/ML Initiative",
      "userId": 8,
      "description": "Implementing AI/ML solutions for Tiruchirappalli region",
      "tasks": [
        {
          "id": 190,
          "projectId": 19,
          "task": "Phase 1 Implementation",
          "status": "Not Started"
        },
        {
          "id": 191,
          "projectId": 19,
          "task": "Phase 2 Implementation",
          "status": "In Progress"
        },
        {
          "id": 192,
          "projectId": 19,
          "task": "Phase 3 Implementation",
          "status": "Completed"
        }
      ]
    },
    {
      "id": 20,
      "name": "Coimbatore Blockchain Initiative",
      "userId": 5,
      "description": "Implementing Blockchain solutions for Coimbatore region",
      "tasks": [
        {
          "id": 200,
          "projectId": 20,
          "task": "Phase 1 Implementation",
          "status": "In Progress"
        },
        {
          "id": 201,
          "projectId": 20,
          "task": "Phase 2 Implementation",
          "status": "In Progress"
        },
        {
          "id": 202,
          "projectId": 20,
          "task": "Phase 3 Implementation",
          "status": "Completed"
        }
      ]
    },
    {
      "id": 21,
      "name": "Madurai Blockchain Initiative",
      "userId": 22,
      "description": "Implementing Blockchain solutions for Madurai region",
      "tasks": [
        {
          "id": 210,
          "projectId": 21,
          "task": "Phase 1 Implementation",
          "status": "Completed"
        },
        {
          "id": 211,
          "projectId": 21,
          "task": "Phase 2 Implementation",
          "status": "Completed"
        }
      ]
    },
    {
      "id": 22,
      "name": "Salem IoT Initiative",
      "userId": 23,
      "description": "Implementing IoT solutions for Salem region",
      "tasks": [
        {
          "id": 220,
          "projectId": 22,
          "task": "Phase 1 Implementation",
          "status": "Completed"
        },
        {
          "id": 221,
          "projectId": 22,
          "task": "Phase 2 Implementation",
          "status": "Not Started"
        }
      ]
    },
    {
      "id": 23,
      "name": "Erode Mobile App Initiative",
      "userId": 50,
      "description": "Implementing Mobile App solutions for Erode region",
      "tasks": [
        {
          "id": 230,
          "projectId": 23,
          "task": "Phase 1 Implementation",
          "status": "In Progress"
        },
        {
          "id": 231,
          "projectId": 23,
          "task": "Phase 2 Implementation",
          "status": "Completed"
        }
      ]
    },
    {
      "id": 24,
      "name": "Erode Mobile App Initiative",
      "userId": 33,
      "description": "Implementing Mobile App solutions for Erode region",
      "tasks": [
        {
          "id": 240,
          "projectId": 24,
          "task": "Phase 1 Implementation",
          "status": "In Progress"
        },
        {
          "id": 241,
          "projectId": 24,
          "task": "Phase 2 Implementation",
          "status": "In Progress"
        },
        {
          "id": 242,
          "projectId": 24,
          "task": "Phase 3 Implementation",
          "status": "In Progress"
        }
      ]
    },
    {
      "id": 25,
      "name": "Neyveli Cloud Computing Initiative",
      "userId": 37,
      "description": "Implementing Cloud Computing solutions for Neyveli region",
      "tasks": [
        {
          "id": 250,
          "projectId": 25,
          "task": "Phase 1 Implementation",
          "status": "In Progress"
        },
        {
          "id": 251,
          "projectId": 25,
          "task": "Phase 2 Implementation",
          "status": "Not Started"
        }
      ]
    },
    {
      "id": 26,
      "name": "Tirunelveli AI/ML Initiative",
      "userId": 47,
      "description": "Implementing AI/ML solutions for Tirunelveli region",
      "tasks": [
        {
          "id": 260,
          "projectId": 26,
          "task": "Phase 1 Implementation",
          "status": "Completed"
        },
        {
          "id": 261,
          "projectId": 26,
          "task": "Phase 2 Implementation",
          "status": "In Progress"
        },
        {
          "id": 262,
          "projectId": 26,
          "task": "Phase 3 Implementation",
          "status": "Not Started"
        },
        {
          "id": 263,
          "projectId": 26,
          "task": "Phase 4 Implementation",
          "status": "Not Started"
        }
      ]
    },
    {
      "id": 27,
      "name": "Neyveli Digital Marketing Initiative",
      "userId": 39,
      "description": "Implementing Digital Marketing solutions for Neyveli region",
      "tasks": [
        {
          "id": 270,
          "projectId": 27,
          "task": "Phase 1 Implementation",
          "status": "Not Started"
        },
        {
          "id": 271,
          "projectId": 27,
          "task": "Phase 2 Implementation",
          "status": "Not Started"
        }
      ]
    },
    {
      "id": 28,
      "name": "Chennai Digital Marketing Initiative",
      "userId": 29,
      "description": "Implementing Digital Marketing solutions for Chennai region",
      "tasks": [
        {
          "id": 280,
          "projectId": 28,
          "task": "Phase 1 Implementation",
          "status": "Completed"
        },
        {
          "id": 281,
          "projectId": 28,
          "task": "Phase 2 Implementation",
          "status": "In Progress"
        }
      ]
    },
    {
      "id": 29,
      "name": "Neyveli Cloud Computing Initiative",
      "userId": 39,
      "description": "Implementing Cloud Computing solutions for Neyveli region",
      "tasks": [
        {
          "id": 290,
          "projectId": 29,
          "task": "Phase 1 Implementation",
          "status": "Not Started"
        },
        {
          "id": 291,
          "projectId": 29,
          "task": "Phase 2 Implementation",
          "status": "Completed"
        },
        {
          "id": 292,
          "projectId": 29,
          "task": "Phase 3 Implementation",
          "status": "In Progress"
        }
      ]
    },
    {
      "id": 30,
      "name": "Erode E-commerce Initiative",
      "userId": 43,
      "description": "Implementing E-commerce solutions for Erode region",
      "tasks": [
        {
          "id": 300,
          "projectId": 30,
          "task": "Phase 1 Implementation",
          "status": "Not Started"
        },
        {
          "id": 301,
          "projectId": 30,
          "task": "Phase 2 Implementation",
          "status": "Not Started"
        }
      ]
    },
    {
      "id": 31,
      "name": "Coimbatore E-commerce Initiative",
      "userId": 43,
      "description": "Implementing E-commerce solutions for Coimbatore region",
      "tasks": [
        {
          "id": 310,
          "projectId": 31,
          "task": "Phase 1 Implementation",
          "status": "Completed"
        },
        {
          "id": 311,
          "projectId": 31,
          "task": "Phase 2 Implementation",
          "status": "Completed"
        },
        {
          "id": 312,
          "projectId": 31,
          "task": "Phase 3 Implementation",
          "status": "Not Started"
        }
      ]
    },
    {
      "id": 32,
      "name": "Salem Cybersecurity Initiative",
      "userId": 45,
      "description": "Implementing Cybersecurity solutions for Salem region",
      "tasks": [
        {
          "id": 320,
          "projectId": 32,
          "task": "Phase 1 Implementation",
          "status": "In Progress"
        },
        {
          "id": 321,
          "projectId": 32,
          "task": "Phase 2 Implementation",
          "status": "In Progress"
        },
        {
          "id": 322,
          "projectId": 32,
          "task": "Phase 3 Implementation",
          "status": "Not Started"
        }
      ]
    },
    {
      "id": 33,
      "name": "Thanjavur IoT Initiative",
      "userId": 12,
      "description": "Implementing IoT solutions for Thanjavur region",
      "tasks": [
        {
          "id": 330,
          "projectId": 33,
          "task": "Phase 1 Implementation",
          "status": "Completed"
        },
        {
          "id": 331,
          "projectId": 33,
          "task": "Phase 2 Implementation",
          "status": "In Progress"
        },
        {
          "id": 332,
          "projectId": 33,
          "task": "Phase 3 Implementation",
          "status": "Not Started"
        },
        {
          "id": 333,
          "projectId": 33,
          "task": "Phase 4 Implementation",
          "status": "Completed"
        }
      ]
    },
    {
      "id": 34,
      "name": "Coimbatore Digital Marketing Initiative",
      "userId": 4,
      "description": "Implementing Digital Marketing solutions for Coimbatore region",
      "tasks": [
        {
          "id": 340,
          "projectId": 34,
          "task": "Phase 1 Implementation",
          "status": "Completed"
        },
        {
          "id": 341,
          "projectId": 34,
          "task": "Phase 2 Implementation",
          "status": "In Progress"
        },
        {
          "id": 342,
          "projectId": 34,
          "task": "Phase 3 Implementation",
          "status": "Completed"
        },
        {
          "id": 343,
          "projectId": 34,
          "task": "Phase 4 Implementation",
          "status": "In Progress"
        }
      ]
    },
    {
      "id": 35,
      "name": "Salem Cybersecurity Initiative",
      "userId": 10,
      "description": "Implementing Cybersecurity solutions for Salem region",
      "tasks": [
        {
          "id": 350,
          "projectId": 35,
          "task": "Phase 1 Implementation",
          "status": "Not Started"
        },
        {
          "id": 351,
          "projectId": 35,
          "task": "Phase 2 Implementation",
          "status": "Not Started"
        },
        {
          "id": 352,
          "projectId": 35,
          "task": "Phase 3 Implementation",
          "status": "Not Started"
        }
      ]
    },
    {
      "id": 36,
      "name": "Coimbatore Blockchain Initiative",
      "userId": 19,
      "description": "Implementing Blockchain solutions for Coimbatore region",
      "tasks": [
        {
          "id": 360,
          "projectId": 36,
          "task": "Phase 1 Implementation",
          "status": "Completed"
        },
        {
          "id": 361,
          "projectId": 36,
          "task": "Phase 2 Implementation",
          "status": "Completed"
        },
        {
          "id": 362,
          "projectId": 36,
          "task": "Phase 3 Implementation",
          "status": "Completed"
        },
        {
          "id": 363,
          "projectId": 36,
          "task": "Phase 4 Implementation",
          "status": "Not Started"
        }
      ]
    },
    {
      "id": 37,
      "name": "Tirunelveli Mobile App Initiative",
      "userId": 3,
      "description": "Implementing Mobile App solutions for Tirunelveli region",
      "tasks": [
        {
          "id": 370,
          "projectId": 37,
          "task": "Phase 1 Implementation",
          "status": "Not Started"
        },
        {
          "id": 371,
          "projectId": 37,
          "task": "Phase 2 Implementation",
          "status": "In Progress"
        }
      ]
    },
    {
      "id": 38,
      "name": "Salem Data Analytics Initiative",
      "userId": 23,
      "description": "Implementing Data Analytics solutions for Salem region",
      "tasks": [
        {
          "id": 380,
          "projectId": 38,
          "task": "Phase 1 Implementation",
          "status": "In Progress"
        },
        {
          "id": 381,
          "projectId": 38,
          "task": "Phase 2 Implementation",
          "status": "Not Started"
        },
        {
          "id": 382,
          "projectId": 38,
          "task": "Phase 3 Implementation",
          "status": "Completed"
        }
      ]
    },
    {
      "id": 39,
      "name": "Tirunelveli IoT Initiative",
      "userId": 31,
      "description": "Implementing IoT solutions for Tirunelveli region",
      "tasks": [
        {
          "id": 390,
          "projectId": 39,
          "task": "Phase 1 Implementation",
          "status": "Not Started"
        },
        {
          "id": 391,
          "projectId": 39,
          "task": "Phase 2 Implementation",
          "status": "In Progress"
        },
        {
          "id": 392,
          "projectId": 39,
          "task": "Phase 3 Implementation",
          "status": "Completed"
        }
      ]
    },
    {
      "id": 40,
      "name": "Thanjavur Cybersecurity Initiative",
      "userId": 33,
      "description": "Implementing Cybersecurity solutions for Thanjavur region",
      "tasks": [
        {
          "id": 400,
          "projectId": 40,
          "task": "Phase 1 Implementation",
          "status": "Not Started"
        },
        {
          "id": 401,
          "projectId": 40,
          "task": "Phase 2 Implementation",
          "status": "In Progress"
        },
        {
          "id": 402,
          "projectId": 40,
          "task": "Phase 3 Implementation",
          "status": "Not Started"
        },
        {
          "id": 403,
          "projectId": 40,
          "task": "Phase 4 Implementation",
          "status": "Not Started"
        }
      ]
    },
    {
      "id": 41,
      "name": "Tiruchirappalli Cybersecurity Initiative",
      "userId": 27,
      "description": "Implementing Cybersecurity solutions for Tiruchirappalli region",
      "tasks": [
        {
          "id": 410,
          "projectId": 41,
          "task": "Phase 1 Implementation",
          "status": "Not Started"
        },
        {
          "id": 411,
          "projectId": 41,
          "task": "Phase 2 Implementation",
          "status": "Completed"
        },
        {
          "id": 412,
          "projectId": 41,
          "task": "Phase 3 Implementation",
          "status": "Not Started"
        },
        {
          "id": 413,
          "projectId": 41,
          "task": "Phase 4 Implementation",
          "status": "In Progress"
        }
      ]
    },
    {
      "id": 42,
      "name": "Vellore Cybersecurity Initiative",
      "userId": 20,
      "description": "Implementing Cybersecurity solutions for Vellore region",
      "tasks": [
        {
          "id": 420,
          "projectId": 42,
          "task": "Phase 1 Implementation",
          "status": "Not Started"
        },
        {
          "id": 421,
          "projectId": 42,
          "task": "Phase 2 Implementation",
          "status": "Completed"
        },
        {
          "id": 422,
          "projectId": 42,
          "task": "Phase 3 Implementation",
          "status": "Completed"
        },
        {
          "id": 423,
          "projectId": 42,
          "task": "Phase 4 Implementation",
          "status": "Not Started"
        }
      ]
    },
    {
      "id": 43,
      "name": "Erode Cloud Computing Initiative",
      "userId": 28,
      "description": "Implementing Cloud Computing solutions for Erode region",
      "tasks": [
        {
          "id": 430,
          "projectId": 43,
          "task": "Phase 1 Implementation",
          "status": "Not Started"
        },
        {
          "id": 431,
          "projectId": 43,
          "task": "Phase 2 Implementation",
          "status": "In Progress"
        }
      ]
    },
    {
      "id": 44,
      "name": "Neyveli Digital Marketing Initiative",
      "userId": 10,
      "description": "Implementing Digital Marketing solutions for Neyveli region",
      "tasks": [
        {
          "id": 440,
          "projectId": 44,
          "task": "Phase 1 Implementation",
          "status": "Not Started"
        },
        {
          "id": 441,
          "projectId": 44,
          "task": "Phase 2 Implementation",
          "status": "Completed"
        },
        {
          "id": 442,
          "projectId": 44,
          "task": "Phase 3 Implementation",
          "status": "Completed"
        }
      ]
    },
    {
      "id": 45,
      "name": "Neyveli Blockchain Initiative",
      "userId": 3,
      "description": "Implementing Blockchain solutions for Neyveli region",
      "tasks": [
        {
          "id": 450,
          "projectId": 45,
          "task": "Phase 1 Implementation",
          "status": "Completed"
        },
        {
          "id": 451,
          "projectId": 45,
          "task": "Phase 2 Implementation",
          "status": "In Progress"
        },
        {
          "id": 452,
          "projectId": 45,
          "task": "Phase 3 Implementation",
          "status": "In Progress"
        }
      ]
    },
    {
      "id": 46,
      "name": "Salem AI/ML Initiative",
      "userId": 8,
      "description": "Implementing AI/ML solutions for Salem region",
      "tasks": [
        {
          "id": 460,
          "projectId": 46,
          "task": "Phase 1 Implementation",
          "status": "Not Started"
        },
        {
          "id": 461,
          "projectId": 46,
          "task": "Phase 2 Implementation",
          "status": "In Progress"
        },
        {
          "id": 462,
          "projectId": 46,
          "task": "Phase 3 Implementation",
          "status": "Not Started"
        },
        {
          "id": 463,
          "projectId": 46,
          "task": "Phase 4 Implementation",
          "status": "Not Started"
        }
      ]
    },
    {
      "id": 47,
      "name": "Neyveli Cybersecurity Initiative",
      "userId": 6,
      "description": "Implementing Cybersecurity solutions for Neyveli region",
      "tasks": [
        {
          "id": 470,
          "projectId": 47,
          "task": "Phase 1 Implementation",
          "status": "In Progress"
        },
        {
          "id": 471,
          "projectId": 47,
          "task": "Phase 2 Implementation",
          "status": "Not Started"
        },
        {
          "id": 472,
          "projectId": 47,
          "task": "Phase 3 Implementation",
          "status": "Completed"
        },
        {
          "id": 473,
          "projectId": 47,
          "task": "Phase 4 Implementation",
          "status": "Not Started"
        }
      ]
    },
    {
      "id": 48,
      "name": "Neyveli E-commerce Initiative",
      "userId": 24,
      "description": "Implementing E-commerce solutions for Neyveli region",
      "tasks": [
        {
          "id": 480,
          "projectId": 48,
          "task": "Phase 1 Implementation",
          "status": "Not Started"
        },
        {
          "id": 481,
          "projectId": 48,
          "task": "Phase 2 Implementation",
          "status": "Completed"
        },
        {
          "id": 482,
          "projectId": 48,
          "task": "Phase 3 Implementation",
          "status": "In Progress"
        },
        {
          "id": 483,
          "projectId": 48,
          "task": "Phase 4 Implementation",
          "status": "Not Started"
        }
      ]
    },
    {
      "id": 49,
      "name": "Tirunelveli E-commerce Initiative",
      "userId": 8,
      "description": "Implementing E-commerce solutions for Tirunelveli region",
      "tasks": [
        {
          "id": 490,
          "projectId": 49,
          "task": "Phase 1 Implementation",
          "status": "Completed"
        },
        {
          "id": 491,
          "projectId": 49,
          "task": "Phase 2 Implementation",
          "status": "Completed"
        }
      ]
    },
    {
      "id": 50,
      "name": "Neyveli Digital Marketing Initiative",
      "userId": 5,
      "description": "Implementing Digital Marketing solutions for Neyveli region",
      "tasks": [
        {
          "id": 500,
          "projectId": 50,
          "task": "Phase 1 Implementation",
          "status": "Completed"
        },
        {
          "id": 501,
          "projectId": 50,
          "task": "Phase 2 Implementation",
          "status": "In Progress"
        },
        {
          "id": 502,
          "projectId": 50,
          "task": "Phase 3 Implementation",
          "status": "Not Started"
        },
        {
          "id": 503,
          "projectId": 50,
          "task": "Phase 4 Implementation",
          "status": "Completed"
        }
      ]
    }
  ],
  "quotes": [
    {
      "author": "A.P.J. Abdul Kalam",
      "quote": "You have to dream before your dreams can come true."
    },
    {
      "author": "A.P.J. Abdul Kalam",
      "quote": "If you want to shine like a sun, first burn like a sun."
    },
    {
      "author": "A.P.J. Abdul Kalam",
      "quote": "Dream, dream, dream. Dreams transform into thoughts and thoughts result in action."
    },
    {
      "author": "Steve Jobs",
      "quote": "Your time is limited, so don't waste it living someone else's life."
    },
    {
      "author": "Steve Jobs",
      "quote": "Innovation distinguishes between a leader and a follower."
    },
    {
      "author": "Steve Jobs",
      "quote": "The people who are crazy enough to think they can change the world are the ones who do."
    },
    {
      "author": "Nelson Mandela",
      "quote": "It always seems impossible until it's done."
    },
    {
      "author": "Nelson Mandela",
      "quote": "Education is the most powerful weapon which you can use to change the world."
    },
    {
      "author": "Mahatma Gandhi",
      "quote": "Be the change that you wish to see in the world."
    },
    {
      "author": "Mahatma Gandhi",
      "quote": "Live as if you were to die tomorrow. Learn as if you were to live forever."
    },
    {
      "author": "Walt Disney",
      "quote": "All our dreams can come true if we have the courage to pursue them."
    },
    {
      "author": "Walt Disney",
      "quote": "The way to get started is to quit talking and begin doing."
    },
    {
      "author": "Rabindranath Tagore",
      "quote": "You can't cross the sea merely by standing and staring at the water."
    },
    {
      "author": "Rabindranath Tagore",
      "quote": "The highest education is that which does not merely give us information but makes our life in harmony with all existence."
    },
    {
      "author": "Swami Vivekananda",
      "quote": "Arise, awake, and stop not until the goal is reached."
    },
    {
      "author": "Swami Vivekananda",
      "quote": "In a conflict between the heart and the brain, follow your heart."
    },
    {
      "author": "Dr. B.R. Ambedkar",
      "quote": "Cultivation of mind should be the ultimate aim of human existence."
    },
    {
      "author": "Dr. B.R. Ambedkar",
      "quote": "I measure the progress of a community by the degree of progress which women have achieved."
    },
    {
      "author": "Kalpana Chawla",
      "quote": "The path from dreams to success does exist. It just has to be driven."
    },
    {
      "author": "Kalpana Chawla",
      "quote": "You are never too old to set another goal or to dream a new dream."
    },
    {
      "author": "Indira Gandhi",
      "quote": "You cannot shake hands with a clenched fist."
    },
    {
      "author": "Indira Gandhi",
      "quote": "The power to question is the basis of all human progress."
    },
    {
      "author": "Albert Einstein",
      "quote": "Life is like riding a bicycle. To keep your balance, you must keep moving."
    },
    {
      "author": "Albert Einstein",
      "quote": "Strive not to be a success, but rather to be of value."
    },
    {
      "author": "Henry Ford",
      "quote": "Whether you think you can or you think you can't, you're right."
    },
    {
      "author": "Henry Ford",
      "quote": "Failure is simply the opportunity to begin again, this time more intelligently."
    },
    {
      "author": "Eleanor Roosevelt",
      "quote": "The future belongs to those who believe in the beauty of their dreams."
    },
    {
      "author": "Eleanor Roosevelt",
      "quote": "You gain strength, courage, and confidence by every experience in which you really stop to look fear in the face."
    },
    {
      "author": "Confucius",
      "quote": "It does not matter how slowly you go as long as you do not stop."
    },
    {
      "author": "Confucius",
      "quote": "Our greatest glory is not in never falling, but in rising every time we fall."
    },
    {
      "author": "Martin Luther King Jr.",
      "quote": "I have a dream that one day this nation will rise up and live out the true meaning of its creed."
    },
    {
      "author": "Martin Luther King Jr.",
      "quote": "The time is always right to do what is right."
    },
    {
      "author": "Ralph Waldo Emerson",
      "quote": "What lies behind us and what lies before us are tiny matters compared to what lies within us."
    },
    {
      "author": "Ralph Waldo Emerson",
      "quote": "To be yourself in a world that is constantly trying to make you something else is the greatest accomplishment."
    },
    {
      "author": "Steve Jobs",
      "quote": "I'm convinced that about half of what separates the successful entrepreneurs from the non-successful ones is pure perseverance."
    },
    {
      "author": "Steve Jobs",
      "quote": "The only way to do great work is to love what you do."
    },
    {
      "author": "A.P.J. Abdul Kalam",
      "quote": "To succeed in your mission, you must have single-minded devotion to your goal."
    },
    {
      "author": "A.P.J. Abdul Kalam",
      "quote": "Let us sacrifice our today so that our children can have a better tomorrow."
    }
  ]
}